{"gtabs":[{"panes":[{"ptabs":[{"history":[{"dir":"/home/luisca/Videos/porn","file":"[Onlyfans] NoodleDude - Ultimate TikTok PMV 2 v1.1.mp4","relpos":3,"ts":1713064936},{"dir":"/home/luisca/Videos","file":"porn","relpos":3,"ts":1713064936},{"dir":"/home/luisca/Videos/porn","file":"[Onlyfans] NoodleDude - Ultimate TikTok PMV 2 v1.1.mp4","relpos":3,"ts":1713064936},{"dir":"/home/luisca/Videos","file":"porn","relpos":3,"ts":1713064936},{"dir":"/home/luisca/Videos/porn","file":"[Onlyfans] NoodleDude - Ultimate TikTok PMV 2 v1.1.mp4","relpos":3,"ts":1713064936},{"dir":"/home/luisca/Videos","file":"porn","relpos":3,"ts":1713064936},{"dir":"/home/luisca/Videos/porn","file":"[Onlyfans] NoodleDude - Ultimate TikTok PMV 2 v1.1.mp4","relpos":3,"ts":1713064936},{"dir":"/home/luisca/Videos","file":"porn","relpos":3,"ts":1713064936},{"dir":"/home/luisca/Videos/porn","file":"[Onlyfans] NoodleDude - Ultimate TikTok PMV 2 v1.1.mp4","relpos":3,"ts":1713064936},{"dir":"/home/luisca/Videos","file":"porn","relpos":3,"ts":1713064936},{"dir":"/home/luisca/Videos/porn","file":"[Onlyfans] NoodleDude - Ultimate TikTok PMV 2 v1.1.mp4","relpos":3,"ts":1713064936},{"dir":"/home/luisca/Videos","file":"porn","relpos":3,"ts":1713064936},{"dir":"/home/luisca/Videos/porn","file":"[Onlyfans] NoodleDude - Ultimate TikTok PMV 2 v1.1.mp4","relpos":3,"ts":1713064936},{"dir":"/home/luisca/Videos","file":"porn","relpos":3,"ts":1713064936},{"dir":"/home/luisca/Videos/porn","file":"[Onlyfans] NoodleDude - Ultimate TikTok PMV 2 v1.1.mp4","relpos":3,"ts":1713064936},{"dir":"/home/luisca/Videos","file":"porn","relpos":3,"ts":1713064936},{"dir":"/home/luisca/Videos/porn","file":"[Onlyfans] NoodleDude - Ultimate TikTok PMV 2 v1.1.mp4","relpos":3,"ts":1713064936},{"dir":"/home/luisca/Videos","file":"porn","relpos":3,"ts":1713064936},{"dir":"/home/luisca/Videos/porn","file":"[Onlyfans] NoodleDude - Ultimate TikTok PMV 2 v1.1.mp4","relpos":3,"ts":1713064936},{"dir":"/home/luisca/Downloads","file":"..","relpos":0,"ts":1713067554},{"dir":"/home/luisca/Documents/obsidian-vaults","file":"test","relpos":4,"ts":1715893920},{"dir":"/home/luisca/Documents/obsidian-vaults/test","file":".obsidian","relpos":1,"ts":1715893920},{"dir":"/home/luisca/Documents/obsidian-vaults/test/.obsidian","file":"plugins","relpos":1,"ts":1715893920},{"dir":"/home/luisca/Documents/obsidian-vaults/test/.obsidian/plugins","file":"obsidian-macros","relpos":8,"ts":1715893920},{"dir":"/home/luisca/Documents/obsidian-vaults","file":"test","relpos":4,"ts":1715893920},{"dir":"/home/luisca/Documents/obsidian-vaults/test","file":".obsidian","relpos":1,"ts":1715893920},{"dir":"/home/luisca/Documents/obsidian-vaults/test/.obsidian","file":"plugins","relpos":1,"ts":1715893920},{"dir":"/home/luisca/Documents/obsidian-vaults/test/.obsidian/plugins","file":"obsidian-macros","relpos":8,"ts":1715893920},{"dir":"/disks/games","file":"The Great PMV Archive","relpos":7,"ts":1717128207},{"dir":"/disks/games/The Great PMV Archive","file":"LMBT","relpos":6,"ts":1717128207},{"dir":"/disks/games/The Great PMV Archive/LMBT","file":"Asians Go Bad - 2k20 Music Video","relpos":1,"ts":1717128207},{"dir":"/disks/games/The Great PMV Archive/LMBT/Asians Go Bad - 2k20 Music Video","file":"Asians Go Bad - 2k20 Music Video (AdultX).mp4","relpos":1,"ts":1717128207},{"dir":"/disks/games/The Great PMV Archive/LMBT","file":"Asians Go Bad - 2k20 Music Video","relpos":1,"ts":1717128207},{"dir":"/disks/games/The Great PMV Archive","file":"Max Bliss","relpos":6,"ts":1717128207},{"dir":"/disks/games/The Great PMV Archive/Max Bliss","file":"..","relpos":0,"ts":1717128207},{"dir":"/disks/games/The Great PMV Archive","file":"Max Bliss","relpos":6,"ts":1717128207},{"dir":"/disks/games/The Great PMV Archive/Max Bliss","file":"Asian Pulsation PMV by Max Bliss 720p.mp4","relpos":1,"ts":1717128207},{"dir":"/disks/games/The Great PMV Archive","file":"Max Bliss","relpos":6,"ts":1717128207},{"dir":"/disks/games/The Great PMV Archive/Max Bliss","file":"Asian Pulsation PMV by Max Bliss 720p.mp4","relpos":1,"ts":1717128207},{"dir":"/disks/games/The Great PMV Archive","file":"MoodyApplePMVs","relpos":6,"ts":1717128207},{"dir":"/disks/games/The Great PMV Archive/MoodyApplePMVs","file":"(Compilations, posters)","relpos":1,"ts":1717128207},{"dir":"/disks/games/The Great PMV Archive/MoodyApplePMVs/(Compilations, posters)","file":"..","relpos":0,"ts":1717128207},{"dir":"/disks/games/The Great PMV Archive/MoodyApplePMVs","file":"PMVs","relpos":2,"ts":1717128207},{"dir":"/disks/games/The Great PMV Archive/MoodyApplePMVs/PMVs","file":"Phase 3","relpos":1,"ts":1717128207},{"dir":"/disks/games/The Great PMV Archive/MoodyApplePMVs/PMVs/Phase 3","file":"..","relpos":0,"ts":1717128207},{"dir":"/disks/games/The Great PMV Archive/MoodyApplePMVs/PMVs","file":"Phase 3","relpos":1,"ts":1717128207},{"dir":"/disks/games/The Great PMV Archive/MoodyApplePMVs","file":"PMVs","relpos":2,"ts":1717128207},{"dir":"/disks/games/The Great PMV Archive","file":"Flyinwombat77","relpos":5,"ts":1717128207},{"dir":"/disks/games/The Great PMV Archive/Flyinwombat77","file":"..","relpos":0,"ts":1717128207},{"dir":"/disks/games/The Great PMV Archive","file":"Big Teasers Entertainment","relpos":4,"ts":1717128207},{"dir":"/disks/games/The Great PMV Archive/Big Teasers Entertainment","file":"..","relpos":0,"ts":1717128207},{"dir":"/disks/games/The Great PMV Archive","file":"BakTsu","relpos":3,"ts":1717128207},{"dir":"/disks/games/The Great PMV Archive/BakTsu","file":"..","relpos":0,"ts":1717128207},{"dir":"/disks/games/The Great PMV Archive","file":"American Spirit","relpos":2,"ts":1717128207},{"dir":"/disks/games/The Great PMV Archive/American Spirit","file":"..","relpos":0,"ts":1717128207},{"dir":"/disks/games/The Great PMV Archive","file":"AM1969","relpos":1,"ts":1717128207},{"dir":"/disks/games/The Great PMV Archive/AM1969","file":"..","relpos":0,"ts":1717128207},{"dir":"/disks/games/The Great PMV Archive","file":"Alexis Texas PMV 4k.mov","relpos":5,"ts":1717128207},{"dir":"/disks/games","file":"pm archive","relpos":10,"ts":1717128209},{"dir":"/disks/games/pm archive","file":"BigChungo451","relpos":1,"ts":1717128209},{"dir":"/disks/games/pm archive/BigChungo451","file":"..","relpos":0,"ts":1717128209},{"dir":"/disks/games/pm archive","file":"BigChungo451","relpos":1,"ts":1717128209},{"dir":"/disks/games","file":"porn","relpos":11,"ts":1717128209},{"dir":"/disks/games/porn","file":"..","relpos":0,"ts":1717128209},{"dir":"/disks/games","file":"The Great PMV Archive","relpos":7,"ts":1717128209},{"dir":"/disks/games/The Great PMV Archive","file":"AM1969","relpos":1,"ts":1717128209},{"dir":"/disks/games/The Great PMV Archive/AM1969","file":"..","relpos":0,"ts":1717128209},{"dir":"/disks/games/The Great PMV Archive","file":"AM1969","relpos":1,"ts":1717128209},{"dir":"/disks/games/The Great PMV Archive/AM1969","file":"SpankBang.com_daddy+a+pmv+by+am1969_1080p.mp4","relpos":1,"ts":1717128209},{"dir":"/disks/games/The Great PMV Archive","file":"Alexis Texas PMV 4k.mov","relpos":5,"ts":1717128209},{"dir":"/disks/games","file":"Documents","relpos":2,"ts":1718496145},{"dir":"/disks/games/Documents","file":"..","relpos":0,"ts":1725294676},{"dir":"/disks/games","file":".Trash-1000","relpos":1,"ts":1725294676},{"dir":"/disks/games/.Trash-1000","file":"files","relpos":2,"ts":1725294676},{"dir":"/disks/games/.Trash-1000/files","file":"ARK Survival Evolved by xatab","relpos":1,"ts":1725294676},{"dir":"/disks/games/.Trash-1000/files/ARK Survival Evolved by xatab","file":".fuse_hidden0000008000000004","relpos":1,"ts":1725294676},{"dir":"/disks/games/.Trash-1000/files","file":"courses","relpos":2,"ts":1725294676},{"dir":"/disks/games/.Trash-1000/files/courses","file":"..","relpos":0,"ts":1725294676},{"dir":"/disks/games/.Trash-1000/files","file":"courses","relpos":2,"ts":1725294676},{"dir":"/disks/games/.Trash-1000","file":"files","relpos":2,"ts":1725294676},{"dir":"/disks/games","file":"..","relpos":0,"ts":1725294676},{"dir":"/disks","file":"games","relpos":1,"ts":1725295426},{"dir":"/","file":"home","relpos":8,"ts":1725295426},{"dir":"/home","file":"luisca","relpos":2,"ts":1725295426},{"dir":"/home/luisca","file":".gnome","relpos":17,"ts":1725295426},{"dir":"/home/luisca/Documents","file":"vs-code-workspaces","relpos":19,"ts":1725295426},{"dir":"/home/luisca/Documents/vs-code-workspaces","file":"..","relpos":0,"ts":1725295426},{"dir":"/home/luisca/Documents","file":"vivaldi-mods","relpos":18,"ts":1725295426},{"dir":"/home/luisca/Documents/vivaldi-mods","file":"..","relpos":0,"ts":1725295426},{"dir":"/home/luisca/Documents","file":"test-vault","relpos":17,"ts":1725295426},{"dir":"/home/luisca/Documents/test-vault","file":"..","relpos":0,"ts":1725295426},{"dir":"/home/luisca/Documents","file":"shared-misc","relpos":16,"ts":1725295426},{"dir":"/home/luisca/Documents/shared-misc","file":"..","relpos":0,"ts":1725295426},{"dir":"/home/luisca/Documents","file":"scripts","relpos":15,"ts":1725295426},{"dir":"/home/luisca/Documents/scripts","file":"..","relpos":0,"ts":1725295426},{"dir":"/home/luisca/Documents","file":"keys","relpos":11,"ts":1725295426},{"dir":"/home/luisca/Documents/keys","file":"..","relpos":0,"ts":1725295426},{"dir":"/home/luisca/Documents","file":"Electronic Arts","relpos":2,"ts":1725295426},{"dir":"/home/luisca","file":"Downloads","relpos":38,"ts":1725295426},{"dir":"/home/luisca/Downloads","file":"2-Figure3-1.png","relpos":1,"ts":1725295426}],"filters":{"invert":true,"dot":false,"manual":"","auto":""},"last-location":"/home/luisca/Downloads","sorting":[2],"preview":false}]},{"ptabs":[{"history":[{"dir":"/home/luisca/Videos","file":"screen-recordings","relpos":3,"ts":1714319922},{"dir":"/home/luisca/Videos/screen-recordings","file":"Peek 2024-03-15 19-34.gif","relpos":8,"ts":1714319922},{"dir":"/home/luisca/Videos","file":"courses","relpos":2,"ts":1714319922},{"dir":"/home/luisca/Videos/courses","file":"RefactoringUI-CompletePackage","relpos":2,"ts":1714319922},{"dir":"/home/luisca/Videos","file":"courses","relpos":2,"ts":1714319922},{"dir":"/home/luisca/Videos/courses","file":"RefactoringUI-CompletePackage","relpos":2,"ts":1714319922},{"dir":"/home/luisca/Videos","file":"courses","relpos":2,"ts":1714319922},{"dir":"/home/luisca/Videos/courses","file":"RefactoringUI-CompletePackage","relpos":2,"ts":1714319922},{"dir":"/home/luisca/Videos/courses/RefactoringUI-CompletePackage","file":"Designing a Complex Form.mp4","relpos":8,"ts":1714319922},{"dir":"/home/luisca/Videos/courses","file":"RefactoringUI-CompletePackage","relpos":2,"ts":1714319922},{"dir":"/home/luisca/Videos","file":"courses","relpos":2,"ts":1714319922},{"dir":"/home/luisca","file":"Videos","relpos":7,"ts":1714319922},{"dir":"/home/luisca/Videos","file":"courses","relpos":2,"ts":1714319922},{"dir":"/home/luisca/Videos/courses","file":"RefactoringUI-CompletePackage","relpos":2,"ts":1714319922},{"dir":"/home/luisca/Videos","file":"..","relpos":0,"ts":1714319922},{"dir":"/home/luisca/p/r","file":"website","relpos":19,"ts":1715037210},{"dir":"/home/luisca/Documents/obsidian-vaults","file":"brain","relpos":1,"ts":1715260704},{"dir":"/home/luisca/Documents/obsidian-vaults/brain","file":"..","relpos":0,"ts":1715260704},{"dir":"/home/luisca/Documents/obsidian-vaults","file":"test","relpos":3,"ts":1715260704},{"dir":"/home/luisca/Documents/obsidian-vaults/test","file":"..","relpos":0,"ts":1715260704},{"dir":"/home/luisca/Documents/obsidian-vaults","file":"plugins-code","relpos":2,"ts":1715260704},{"dir":"/home/luisca/Documents/obsidian-vaults/plugins-code","file":"..","relpos":0,"ts":1715260704},{"dir":"/home/luisca/Documents/obsidian-vaults","file":"plugins-code","relpos":2,"ts":1715260704},{"dir":"/home/luisca/Documents/obsidian-vaults/plugins-code","file":"..","relpos":0,"ts":1715260704},{"dir":"/home/luisca/Documents/obsidian-vaults","file":"test","relpos":3,"ts":1715260704},{"dir":"/home/luisca/Documents/obsidian-vaults/test","file":"..","relpos":0,"ts":1715260704},{"dir":"/home/luisca/Documents/obsidian-vaults","file":"brain","relpos":1,"ts":1715260704},{"dir":"/home/luisca/Documents/obsidian-vaults/brain","file":"..","relpos":0,"ts":1715260704},{"dir":"/home/luisca/Documents/obsidian-vaults","file":"plugins-code","relpos":2,"ts":1715260704},{"dir":"/home/luisca/Documents/obsidian-vaults/plugins-code","file":"..","relpos":0,"ts":1715260704},{"dir":"/home/luisca/Documents/obsidian-vaults","file":"test","relpos":3,"ts":1715260704},{"dir":"/home/luisca/Documents/obsidian-vaults/test","file":".obsidian","relpos":1,"ts":1715260704},{"dir":"/home/luisca/Documents/obsidian-vaults/test/.obsidian","file":"..","relpos":0,"ts":1715260704},{"dir":"/home/luisca/Documents/obsidian-vaults/test","file":".obsidian","relpos":1,"ts":1715260704},{"dir":"/home/luisca/Documents/obsidian-vaults","file":"test","relpos":3,"ts":1715260704},{"dir":"/home/luisca/Documents/obsidian-vaults/test","file":".obsidian","relpos":1,"ts":1715260704},{"dir":"/home/luisca/Documents/obsidian-vaults/test/.obsidian","file":"..","relpos":0,"ts":1715260704},{"dir":"/home/luisca/Documents/obsidian-vaults/test","file":".obsidian","relpos":1,"ts":1715260704},{"dir":"/home/luisca/Documents/obsidian-vaults","file":"test","relpos":3,"ts":1715260704},{"dir":"/home/luisca/Documents/obsidian-vaults/test","file":".obsidian","relpos":1,"ts":1715260704},{"dir":"/home/luisca/Documents/obsidian-vaults/test/.obsidian","file":"app.json","relpos":3,"ts":1715260704},{"dir":"/home/luisca/Documents/obsidian-vaults/test","file":".obsidian","relpos":1,"ts":1715260704},{"dir":"/home/luisca/Documents/obsidian-vaults","file":"test","relpos":3,"ts":1715260704},{"dir":"/home/luisca/Documents","file":"test-vault","relpos":17,"ts":1715260704},{"dir":"/home/luisca/Documents/test-vault","file":".obsidian","relpos":1,"ts":1715260704},{"dir":"/home/luisca/Documents/test-vault/.obsidian","file":"bookmarks.json","relpos":3,"ts":1715260704},{"dir":"/home/luisca/Documents/obsidian-vaults","file":"brain","relpos":1,"ts":1715260704},{"dir":"/home/luisca/Documents/obsidian-vaults/brain","file":"..","relpos":0,"ts":1715260704},{"dir":"/home/luisca/Documents/obsidian-vaults","file":"test","relpos":3,"ts":1715260704},{"dir":"/home/luisca/Documents/obsidian-vaults/test","file":"..","relpos":0,"ts":1715260704},{"dir":"/home/luisca/Documents/obsidian-vaults","file":"plugins-code","relpos":2,"ts":1715260704},{"dir":"/home/luisca/Documents/obsidian-vaults/plugins-code","file":"..","relpos":0,"ts":1715260704},{"dir":"/home/luisca/Documents/obsidian-vaults","file":"plugins-code","relpos":2,"ts":1715260704},{"dir":"/home/luisca/Documents/obsidian-vaults/plugins-code","file":"..","relpos":0,"ts":1715260704},{"dir":"/home/luisca/Documents/obsidian-vaults","file":"test","relpos":3,"ts":1715260704},{"dir":"/home/luisca/Documents/obsidian-vaults/test","file":"..","relpos":0,"ts":1715260704},{"dir":"/home/luisca/Documents/obsidian-vaults","file":"brain","relpos":1,"ts":1715260704},{"dir":"/home/luisca/Documents/obsidian-vaults/brain","file":"..","relpos":0,"ts":1715260704},{"dir":"/home/luisca/Documents/obsidian-vaults","file":"plugins-code","relpos":2,"ts":1715260704},{"dir":"/home/luisca/Documents/obsidian-vaults/plugins-code","file":"..","relpos":0,"ts":1715260704},{"dir":"/home/luisca/Documents/obsidian-vaults","file":"test","relpos":3,"ts":1715260704},{"dir":"/home/luisca/Documents/obsidian-vaults/test","file":".obsidian","relpos":1,"ts":1715260704},{"dir":"/home/luisca/Documents/obsidian-vaults/test/.obsidian","file":"..","relpos":0,"ts":1715260704},{"dir":"/home/luisca/Documents/obsidian-vaults/test","file":".obsidian","relpos":1,"ts":1715260704},{"dir":"/home/luisca/Documents/obsidian-vaults","file":"test","relpos":3,"ts":1715260704},{"dir":"/home/luisca/Documents/obsidian-vaults/test","file":".obsidian","relpos":1,"ts":1715260704},{"dir":"/home/luisca/Documents/obsidian-vaults/test/.obsidian","file":"..","relpos":0,"ts":1715260704},{"dir":"/home/luisca/Documents/obsidian-vaults/test","file":".obsidian","relpos":1,"ts":1715260704},{"dir":"/home/luisca/Documents/obsidian-vaults","file":"test","relpos":3,"ts":1715260704},{"dir":"/home/luisca/Documents/obsidian-vaults/test","file":".obsidian","relpos":1,"ts":1715260704},{"dir":"/home/luisca/Documents/obsidian-vaults/test/.obsidian","file":"app.json","relpos":3,"ts":1715260704},{"dir":"/home/luisca/Documents/obsidian-vaults/test","file":".obsidian","relpos":1,"ts":1715260704},{"dir":"/home/luisca/Documents/obsidian-vaults","file":"test","relpos":3,"ts":1715260704},{"dir":"/home/luisca/Documents","file":"test-vault","relpos":17,"ts":1715260704},{"dir":"/home/luisca/Documents/test-vault","file":".obsidian","relpos":1,"ts":1715260704},{"dir":"/home/luisca/Documents/test-vault/.obsidian","file":"bookmarks.json","relpos":3,"ts":1715260704},{"dir":"/home/luisca/p","file":"nexa-prep","relpos":6,"ts":1715301695},{"dir":"/home/luisca/p/nexa-prep","file":"user-stories.md","relpos":8,"ts":1715301695},{"dir":"/home/luisca/p","file":"nexa-prep","relpos":6,"ts":1715301695},{"dir":"/home/luisca/p/nexa-prep","file":"user-stories.md","relpos":8,"ts":1715301695},{"dir":"/home/luisca/p","file":"r","relpos":1,"ts":1715384911},{"dir":"/home/luisca/p/r","file":"test","relpos":1,"ts":1715384911},{"dir":"/home/luisca/p","file":"r","relpos":1,"ts":1715384911},{"dir":"/home/luisca","file":"p","relpos":11,"ts":1715384911},{"dir":"/home/luisca/p","file":"r","relpos":1,"ts":1715384911},{"dir":"/home/luisca","file":"p","relpos":11,"ts":1715384911},{"dir":"/home/luisca/p","file":"r","relpos":1,"ts":1715384911},{"dir":"/home/luisca","file":"p","relpos":11,"ts":1715384911},{"dir":"/home/luisca/p","file":"nexa-prep","relpos":1,"ts":1715384911},{"dir":"/home/luisca/p/nexa-prep","file":".git","relpos":1,"ts":1715384911},{"dir":"/home/luisca/p","file":"r","relpos":1,"ts":1715384911},{"dir":"/home/luisca/p/r","file":"test","relpos":1,"ts":1715384911},{"dir":"/home/luisca/p","file":"r","relpos":1,"ts":1715384911},{"dir":"/home/luisca","file":"p","relpos":11,"ts":1715384911},{"dir":"/home/luisca/p","file":"r","relpos":1,"ts":1715384911},{"dir":"/home/luisca","file":"p","relpos":11,"ts":1715384911},{"dir":"/home/luisca/p","file":"r","relpos":1,"ts":1715384911},{"dir":"/home/luisca","file":"p","relpos":11,"ts":1715384911},{"dir":"/home/luisca/p","file":"nexa-prep","relpos":1,"ts":1715384911},{"dir":"/home/luisca/p/nexa-prep","file":".git","relpos":1,"ts":1715384911}],"filters":{"invert":true,"dot":false,"manual":"","auto":""},"last-location":"/home/luisca/p/nexa-prep","sorting":[2],"preview":false}]}],"active-pane":0,"preview":false,"splitter":{"pos":-1,"ratio":0.5,"orientation":"v","expanded":true}}],"trash":[{"trashed":"/home/luisca/.local/share/vifm/Trash/000_AM1969","original":"/disks/games/The Great PMV Archive/AM1969"},{"trashed":"/home/luisca/.local/share/vifm/Trash/000_American Spirit","original":"/disks/games/The Great PMV Archive/American Spirit"},{"trashed":"/home/luisca/.local/share/vifm/Trash/000_BakTsu","original":"/disks/games/The Great PMV Archive/BakTsu"},{"trashed":"/home/luisca/.local/share/vifm/Trash/000_Big Teasers Entertainment","original":"/disks/games/The Great PMV Archive/Big Teasers Entertainment"},{"trashed":"/home/luisca/.local/share/vifm/Trash/000_Flyinwombat77","original":"/disks/games/The Great PMV Archive/Flyinwombat77"},{"trashed":"/home/luisca/.local/share/vifm/Trash/000_LMBT","original":"/disks/games/The Great PMV Archive/LMBT"},{"trashed":"/home/luisca/.local/share/vifm/Trash/000_Max Bliss","original":"/disks/games/The Great PMV Archive/Max Bliss"},{"trashed":"/home/luisca/.local/share/vifm/Trash/000_MoodyApplePMVs","original":"/disks/games/The Great PMV Archive/MoodyApplePMVs"},{"trashed":"/home/luisca/.local/share/vifm/Trash/000_rofi","original":"/home/luisca/.config/awesome/rofi"},{"trashed":"/home/luisca/.local/share/vifm/Trash/000_github-copilot","original":"/home/luisca/.config/github-copilot"},{"trashed":"/home/luisca/.local/share/vifm/Trash/000_google-chrome","original":"/home/luisca/.config/google-chrome"},{"trashed":"/home/luisca/.local/share/vifm/Trash/000_lutris","original":"/home/luisca/.config/lutris"},{"trashed":"/home/luisca/.local/share/vifm/Trash/000_picom","original":"/home/luisca/.config/picom"},{"trashed":"/home/luisca/.local/share/vifm/Trash/000_config.rasi","original":"/home/luisca/.config/rofi/config.rasi"},{"trashed":"/home/luisca/.local/share/vifm/Trash/000_squared-everforest.rasi","original":"/home/luisca/.config/rofi/squared-everforest.rasi"},{"trashed":"/home/luisca/.local/share/vifm/Trash/000_Default.vifm","original":"/home/luisca/.config/vifm/colors/Default.vifm"},{"trashed":"/home/luisca/.local/share/vifm/Trash/000_afterglow.vifm","original":"/home/luisca/.config/vifm/colors/afterglow.vifm"},{"trashed":"/home/luisca/.local/share/vifm/Trash/000_ansa.vifm","original":"/home/luisca/.config/vifm/colors/ansa.vifm"},{"trashed":"/home/luisca/.local/share/vifm/Trash/000_astrell.vifm","original":"/home/luisca/.config/vifm/colors/astrell.vifm"},{"trashed":"/home/luisca/.local/share/vifm/Trash/000_create_themes.md","original":"/home/luisca/.config/vifm/colors/create_themes.md"},{"trashed":"/home/luisca/.local/share/vifm/Trash/000_crown_24bit.vifm","original":"/home/luisca/.config/vifm/colors/crown_24bit.vifm"},{"trashed":"/home/luisca/.local/share/vifm/Trash/000_darkdesert.vifm","original":"/home/luisca/.config/vifm/colors/darkdesert.vifm"},{"trashed":"/home/luisca/.local/share/vifm/Trash/000_desert.vifm","original":"/home/luisca/.config/vifm/colors/desert.vifm"},{"trashed":"/home/luisca/.local/share/vifm/Trash/000_dracula.vifm","original":"/home/luisca/.config/vifm/colors/dracula.vifm"},{"trashed":"/home/luisca/.local/share/vifm/Trash/000_dwmlight.vifm","original":"/home/luisca/.config/vifm/colors/dwmlight.vifm"},{"trashed":"/home/luisca/.local/share/vifm/Trash/000_fargo.vifm","original":"/home/luisca/.config/vifm/colors/fargo.vifm"},{"trashed":"/home/luisca/.local/share/vifm/Trash/000_g80.vifm","original":"/home/luisca/.config/vifm/colors/g80.vifm"},{"trashed":"/home/luisca/.local/share/vifm/Trash/000_gruvbox.vifm","original":"/home/luisca/.config/vifm/colors/gruvbox.vifm"},{"trashed":"/home/luisca/.local/share/vifm/Trash/000_iceberg.vifm","original":"/home/luisca/.config/vifm/colors/iceberg.vifm"},{"trashed":"/home/luisca/.local/share/vifm/Trash/000_lucius.vifm","original":"/home/luisca/.config/vifm/colors/lucius.vifm"},{"trashed":"/home/luisca/.local/share/vifm/Trash/000_matrix.vifm","original":"/home/luisca/.config/vifm/colors/matrix.vifm"},{"trashed":"/home/luisca/.local/share/vifm/Trash/000_mc-like.vifm","original":"/home/luisca/.config/vifm/colors/mc-like.vifm"},{"trashed":"/home/luisca/.local/share/vifm/Trash/000_molokai.vifm","original":"/home/luisca/.config/vifm/colors/molokai.vifm"},{"trashed":"/home/luisca/.local/share/vifm/Trash/000_monochrome.vifm","original":"/home/luisca/.config/vifm/colors/monochrome.vifm"},{"trashed":"/home/luisca/.local/share/vifm/Trash/000_near-default.vifm","original":"/home/luisca/.config/vifm/colors/near-default.vifm"},{"trashed":"/home/luisca/.local/share/vifm/Trash/000_nord.vifm","original":"/home/luisca/.config/vifm/colors/nord.vifm"},{"trashed":"/home/luisca/.local/share/vifm/Trash/000_onedark.vifm","original":"/home/luisca/.config/vifm/colors/onedark.vifm"},{"trashed":"/home/luisca/.local/share/vifm/Trash/000_palenight.vifm","original":"/home/luisca/.config/vifm/colors/palenight.vifm"},{"trashed":"/home/luisca/.local/share/vifm/Trash/000_paper.vifm","original":"/home/luisca/.config/vifm/colors/paper.vifm"},{"trashed":"/home/luisca/.local/share/vifm/Trash/000_papercolor-dark.vifm","original":"/home/luisca/.config/vifm/colors/papercolor-dark.vifm"},{"trashed":"/home/luisca/.local/share/vifm/Trash/000_papercolor-light.vifm","original":"/home/luisca/.config/vifm/colors/papercolor-light.vifm"},{"trashed":"/home/luisca/.local/share/vifm/Trash/000_ph.vifm","original":"/home/luisca/.config/vifm/colors/ph.vifm"},{"trashed":"/home/luisca/.local/share/vifm/Trash/000_reicheltd-light.vifm","original":"/home/luisca/.config/vifm/colors/reicheltd-light.vifm"},{"trashed":"/home/luisca/.local/share/vifm/Trash/000_sandy.vifm","original":"/home/luisca/.config/vifm/colors/sandy.vifm"},{"trashed":"/home/luisca/.local/share/vifm/Trash/000_semidarkdesert.vifm","original":"/home/luisca/.config/vifm/colors/semidarkdesert.vifm"},{"trashed":"/home/luisca/.local/share/vifm/Trash/000_snowwhite.vifm","original":"/home/luisca/.config/vifm/colors/snowwhite.vifm"},{"trashed":"/home/luisca/.local/share/vifm/Trash/000_solarized-dark.vifm","original":"/home/luisca/.config/vifm/colors/solarized-dark.vifm"},{"trashed":"/home/luisca/.local/share/vifm/Trash/000_solarized-light.vifm","original":"/home/luisca/.config/vifm/colors/solarized-light.vifm"},{"trashed":"/home/luisca/.local/share/vifm/Trash/000_truedark.vifm","original":"/home/luisca/.config/vifm/colors/truedark.vifm"},{"trashed":"/home/luisca/.local/share/vifm/Trash/000_zenburn.vifm","original":"/home/luisca/.config/vifm/colors/zenburn.vifm"},{"trashed":"/home/luisca/.local/share/vifm/Trash/000_zenburn_1.vifm","original":"/home/luisca/.config/vifm/colors/zenburn_1.vifm"},{"trashed":"/home/luisca/.local/share/vifm/Trash/002_config.rasi","original":"/home/luisca/.local/share/rofi/themes/config.rasi"},{"trashed":"/home/luisca/.local/share/vifm/Trash/000_Obsidian Vault","original":"/home/luisca/Documents/Obsidian Vault"},{"trashed":"/home/luisca/.local/share/vifm/Trash/000_.obsidian","original":"/home/luisca/Documents/obsidian-vaults/.obsidian"},{"trashed":"/home/luisca/.local/share/vifm/Trash/000_.stfolder","original":"/home/luisca/Documents/obsidian-vaults/.stfolder"},{"trashed":"/home/luisca/.local/share/vifm/Trash/000_.stignore","original":"/home/luisca/Documents/obsidian-vaults/.stignore"},{"trashed":"/home/luisca/.local/share/vifm/Trash/000_.trash","original":"/home/luisca/Documents/obsidian-vaults/test/.trash"},{"trashed":"/home/luisca/.local/share/vifm/Trash/000_.stfolder","original":"/home/luisca/Documents/shared-misc/.stfolder"},{"trashed":"/home/luisca/.local/share/vifm/Trash/000_Annotations for “The Three-Body Problem”.json","original":"/home/luisca/Documents/shared-misc/Annotations for “The Three-Body Problem”.json"},{"trashed":"/home/luisca/.local/share/vifm/Trash/000_Doom Eternal [P] [RUS + ENG + 11 RUS + ENG + 8] (2020, FPS) (Build 11905845 + 16 DLC) [Portable] [rutracker-5868220].torrent","original":"/home/luisca/Documents/shared-misc/Doom Eternal [P] [RUS + ENG + 11 RUS + ENG + 8] (2020, FPS) (Build 11905845 + 16 DLC) [Portable] [rutracker-5868220].torrent"},{"trashed":"/home/luisca/.local/share/vifm/Trash/000_inetutils-1.4.0","original":"/home/luisca/Documents/shared-misc/inetutils-1.4.0"},{"trashed":"/home/luisca/.local/share/vifm/Trash/000_inetutils-1.4.0.tar.gz","original":"/home/luisca/Documents/shared-misc/inetutils-1.4.0.tar.gz"},{"trashed":"/home/luisca/.local/share/vifm/Trash/000_openwrt-19.07.10-brcm63xx-generic-96328avng-generic-squashfs-cfe-8M.bin","original":"/home/luisca/Documents/shared-misc/openwrt-19.07.10-brcm63xx-generic-96328avng-generic-squashfs-cfe-8M.bin"},{"trashed":"/home/luisca/.local/share/vifm/Trash/000_smart-yellow-candy","original":"/home/luisca/Documents/shared-misc/smart-yellow-candy"},{"trashed":"/home/luisca/.local/share/vifm/Trash/000_smart-yellow-candy.zip","original":"/home/luisca/Documents/shared-misc/smart-yellow-candy.zip"},{"trashed":"/home/luisca/.local/share/vifm/Trash/000_the-great-pmv-archive.torrent","original":"/home/luisca/Documents/shared-misc/the-great-pmv-archive.torrent"},{"trashed":"/home/luisca/.local/share/vifm/Trash/000_test","original":"/home/luisca/Documents/test"},{"trashed":"/home/luisca/.local/share/vifm/Trash/000_test1.md","original":"/home/luisca/Documents/test1.md"},{"trashed":"/home/luisca/.local/share/vifm/Trash/000_dotfiles.code-workspace","original":"/home/luisca/Documents/vifm-tests/dotfiles.code-workspace"},{"trashed":"/home/luisca/.local/share/vifm/Trash/001_dotfiles.code-workspace","original":"/home/luisca/Documents/vifm-tests/dotfiles.code-workspace"},{"trashed":"/home/luisca/.local/share/vifm/Trash/000_https-proxy-agent-test.code-workspace","original":"/home/luisca/Documents/vifm-tests/https-proxy-agent-test.code-workspace"},{"trashed":"/home/luisca/.local/share/vifm/Trash/000_idk.md","original":"/home/luisca/Documents/vifm-tests/idk.md"},{"trashed":"/home/luisca/.local/share/vifm/Trash/000_idk2.md","original":"/home/luisca/Documents/vifm-tests/idk2.md"},{"trashed":"/home/luisca/.local/share/vifm/Trash/000_obsidian-calendar-ui.code-workspace","original":"/home/luisca/Documents/vifm-tests/obsidian-calendar-ui.code-workspace"},{"trashed":"/home/luisca/.local/share/vifm/Trash/000_obsidian-daily-note-flex-plugin.code-workspace","original":"/home/luisca/Documents/vifm-tests/obsidian-daily-note-flex-plugin.code-workspace"},{"trashed":"/home/luisca/.local/share/vifm/Trash/000_obsidian-daily-notes-interface.code-workspace","original":"/home/luisca/Documents/vifm-tests/obsidian-daily-notes-interface.code-workspace"},{"trashed":"/home/luisca/.local/share/vifm/Trash/000_src","original":"/home/luisca/Documents/vifm-tests/src"},{"trashed":"/home/luisca/.local/share/vifm/Trash/001_test","original":"/home/luisca/Documents/vifm-tests/test"},{"trashed":"/home/luisca/.local/share/vifm/Trash/000_test(1).md","original":"/home/luisca/Documents/vifm-tests/test(1).md"},{"trashed":"/home/luisca/.local/share/vifm/Trash/001_test(1).md","original":"/home/luisca/Documents/vifm-tests/test(1).md"},{"trashed":"/home/luisca/.local/share/vifm/Trash/002_test(1).md","original":"/home/luisca/Documents/vifm-tests/test(1).md"},{"trashed":"/home/luisca/.local/share/vifm/Trash/000_test(10).md","original":"/home/luisca/Documents/vifm-tests/test(10).md"},{"trashed":"/home/luisca/.local/share/vifm/Trash/001_test(10).md","original":"/home/luisca/Documents/vifm-tests/test(10).md"},{"trashed":"/home/luisca/.local/share/vifm/Trash/002_test(10).md","original":"/home/luisca/Documents/vifm-tests/test(10).md"},{"trashed":"/home/luisca/.local/share/vifm/Trash/003_test(10).md","original":"/home/luisca/Documents/vifm-tests/test(10).md"},{"trashed":"/home/luisca/.local/share/vifm/Trash/000_test(2).md","original":"/home/luisca/Documents/vifm-tests/test(2).md"},{"trashed":"/home/luisca/.local/share/vifm/Trash/001_test(2).md","original":"/home/luisca/Documents/vifm-tests/test(2).md"},{"trashed":"/home/luisca/.local/share/vifm/Trash/000_test(3).md","original":"/home/luisca/Documents/vifm-tests/test(3).md"},{"trashed":"/home/luisca/.local/share/vifm/Trash/001_test(3).md","original":"/home/luisca/Documents/vifm-tests/test(3).md"},{"trashed":"/home/luisca/.local/share/vifm/Trash/000_test(4).md","original":"/home/luisca/Documents/vifm-tests/test(4).md"},{"trashed":"/home/luisca/.local/share/vifm/Trash/001_test(4).md","original":"/home/luisca/Documents/vifm-tests/test(4).md"},{"trashed":"/home/luisca/.local/share/vifm/Trash/000_test(5).md","original":"/home/luisca/Documents/vifm-tests/test(5).md"},{"trashed":"/home/luisca/.local/share/vifm/Trash/001_test(5).md","original":"/home/luisca/Documents/vifm-tests/test(5).md"},{"trashed":"/home/luisca/.local/share/vifm/Trash/000_test(6).md","original":"/home/luisca/Documents/vifm-tests/test(6).md"},{"trashed":"/home/luisca/.local/share/vifm/Trash/001_test(6).md","original":"/home/luisca/Documents/vifm-tests/test(6).md"},{"trashed":"/home/luisca/.local/share/vifm/Trash/000_test(7).md","original":"/home/luisca/Documents/vifm-tests/test(7).md"},{"trashed":"/home/luisca/.local/share/vifm/Trash/001_test(7).md","original":"/home/luisca/Documents/vifm-tests/test(7).md"},{"trashed":"/home/luisca/.local/share/vifm/Trash/000_test(8).md","original":"/home/luisca/Documents/vifm-tests/test(8).md"},{"trashed":"/home/luisca/.local/share/vifm/Trash/001_test(8).md","original":"/home/luisca/Documents/vifm-tests/test(8).md"},{"trashed":"/home/luisca/.local/share/vifm/Trash/002_test(8).md","original":"/home/luisca/Documents/vifm-tests/test(8).md"},{"trashed":"/home/luisca/.local/share/vifm/Trash/000_test(9).md","original":"/home/luisca/Documents/vifm-tests/test(9).md"},{"trashed":"/home/luisca/.local/share/vifm/Trash/001_test(9).md","original":"/home/luisca/Documents/vifm-tests/test(9).md"},{"trashed":"/home/luisca/.local/share/vifm/Trash/002_test(9).md","original":"/home/luisca/Documents/vifm-tests/test(9).md"},{"trashed":"/home/luisca/.local/share/vifm/Trash/003_test(9).md","original":"/home/luisca/Documents/vifm-tests/test(9).md"},{"trashed":"/home/luisca/.local/share/vifm/Trash/000_test-renamed(1).md","original":"/home/luisca/Documents/vifm-tests/test-renamed(1).md"},{"trashed":"/home/luisca/.local/share/vifm/Trash/000_test-renamed(2).md","original":"/home/luisca/Documents/vifm-tests/test-renamed(2).md"},{"trashed":"/home/luisca/.local/share/vifm/Trash/000_test-renamed(3).md","original":"/home/luisca/Documents/vifm-tests/test-renamed(3).md"},{"trashed":"/home/luisca/.local/share/vifm/Trash/000_test-renamed(4).md","original":"/home/luisca/Documents/vifm-tests/test-renamed(4).md"},{"trashed":"/home/luisca/.local/share/vifm/Trash/000_test-renamed(5).md","original":"/home/luisca/Documents/vifm-tests/test-renamed(5).md"},{"trashed":"/home/luisca/.local/share/vifm/Trash/000_test-renamed.md","original":"/home/luisca/Documents/vifm-tests/test-renamed.md"},{"trashed":"/home/luisca/.local/share/vifm/Trash/000_test.md","original":"/home/luisca/Documents/vifm-tests/test.md"},{"trashed":"/home/luisca/.local/share/vifm/Trash/002_test.md","original":"/home/luisca/Documents/vifm-tests/test.md"},{"trashed":"/home/luisca/.local/share/vifm/Trash/002_test(2).md","original":"/home/luisca/Documents/vifm-tests/test/test(2).md"},{"trashed":"/home/luisca/.local/share/vifm/Trash/002_test(3).md","original":"/home/luisca/Documents/vifm-tests/test/test(3).md"},{"trashed":"/home/luisca/.local/share/vifm/Trash/002_test(4).md","original":"/home/luisca/Documents/vifm-tests/test/test(4).md"},{"trashed":"/home/luisca/.local/share/vifm/Trash/002_test(5).md","original":"/home/luisca/Documents/vifm-tests/test/test(5).md"},{"trashed":"/home/luisca/.local/share/vifm/Trash/002_test(6).md","original":"/home/luisca/Documents/vifm-tests/test/test(6).md"},{"trashed":"/home/luisca/.local/share/vifm/Trash/002_test(7).md","original":"/home/luisca/Documents/vifm-tests/test/test(7).md"},{"trashed":"/home/luisca/.local/share/vifm/Trash/003_test(8).md","original":"/home/luisca/Documents/vifm-tests/test/test(8).md"},{"trashed":"/home/luisca/.local/share/vifm/Trash/001_test.md","original":"/home/luisca/Documents/vifm-tests/test/test.md"},{"trashed":"/home/luisca/.local/share/vifm/Trash/000_test2.md","original":"/home/luisca/Documents/vifm-tests/test2.md"},{"trashed":"/home/luisca/.local/share/vifm/Trash/000_test3(1).md","original":"/home/luisca/Documents/vifm-tests/test3(1).md"},{"trashed":"/home/luisca/.local/share/vifm/Trash/000_test3(10).md","original":"/home/luisca/Documents/vifm-tests/test3(10).md"},{"trashed":"/home/luisca/.local/share/vifm/Trash/000_test3(11).md","original":"/home/luisca/Documents/vifm-tests/test3(11).md"},{"trashed":"/home/luisca/.local/share/vifm/Trash/000_test3(12).md","original":"/home/luisca/Documents/vifm-tests/test3(12).md"},{"trashed":"/home/luisca/.local/share/vifm/Trash/000_test3(13).md","original":"/home/luisca/Documents/vifm-tests/test3(13).md"},{"trashed":"/home/luisca/.local/share/vifm/Trash/000_test3(14).md","original":"/home/luisca/Documents/vifm-tests/test3(14).md"},{"trashed":"/home/luisca/.local/share/vifm/Trash/000_test3(15).md","original":"/home/luisca/Documents/vifm-tests/test3(15).md"},{"trashed":"/home/luisca/.local/share/vifm/Trash/000_test3(2).md","original":"/home/luisca/Documents/vifm-tests/test3(2).md"},{"trashed":"/home/luisca/.local/share/vifm/Trash/000_test3(3).md","original":"/home/luisca/Documents/vifm-tests/test3(3).md"},{"trashed":"/home/luisca/.local/share/vifm/Trash/000_test3(4).md","original":"/home/luisca/Documents/vifm-tests/test3(4).md"},{"trashed":"/home/luisca/.local/share/vifm/Trash/000_test3(5).md","original":"/home/luisca/Documents/vifm-tests/test3(5).md"},{"trashed":"/home/luisca/.local/share/vifm/Trash/000_test3(6).md","original":"/home/luisca/Documents/vifm-tests/test3(6).md"},{"trashed":"/home/luisca/.local/share/vifm/Trash/000_test3(7).md","original":"/home/luisca/Documents/vifm-tests/test3(7).md"},{"trashed":"/home/luisca/.local/share/vifm/Trash/000_test3(8).md","original":"/home/luisca/Documents/vifm-tests/test3(8).md"},{"trashed":"/home/luisca/.local/share/vifm/Trash/000_test3(9).md","original":"/home/luisca/Documents/vifm-tests/test3(9).md"},{"trashed":"/home/luisca/.local/share/vifm/Trash/000_test3.md","original":"/home/luisca/Documents/vifm-tests/test3.md"},{"trashed":"/home/luisca/.local/share/vifm/Trash/000_65a70ffe90be8822f6a50647.mp4","original":"/home/luisca/Downloads/65a70ffe90be8822f6a50647.mp4"},{"trashed":"/home/luisca/.local/share/vifm/Trash/000_Component prop types example.mp4","original":"/home/luisca/Downloads/Component prop types example.mp4"},{"trashed":"/home/luisca/.local/share/vifm/Trash/000_EPORNER.COM - [G4YhtM1kPUi] NoodleDude Cock Hero - PMV 60FPS 4K (1080).mp4","original":"/home/luisca/Downloads/EPORNER.COM - [G4YhtM1kPUi] NoodleDude Cock Hero - PMV 60FPS 4K (1080).mp4"},{"trashed":"/home/luisca/.local/share/vifm/Trash/000_POVPerv.24.03.14.Riley.Reid.XXX.1080p.HEVC.x265.PRT.mkv","original":"/home/luisca/Downloads/POVPerv.24.03.14.Riley.Reid.XXX.1080p.HEVC.x265.PRT.mkv"},{"trashed":"/home/luisca/.local/share/vifm/Trash/000_POVPerv.24.03.14.Riley.Reid.XXX.1080p.HEVC.x265.PRT[XvX]","original":"/home/luisca/Downloads/POVPerv.24.03.14.Riley.Reid.XXX.1080p.HEVC.x265.PRT[XvX]"},{"trashed":"/home/luisca/.local/share/vifm/Trash/000_PornRips.to - HEVC x265 Porn.nfo","original":"/home/luisca/Downloads/POVPerv.24.03.14.Riley.Reid.XXX.1080p.HEVC.x265.PRT[XvX]/PornRips.to - HEVC x265 Porn.nfo"},{"trashed":"/home/luisca/.local/share/vifm/Trash/000_[XvX]Endorsed by torrentgalaxy.to .nfo","original":"/home/luisca/Downloads/POVPerv.24.03.14.Riley.Reid.XXX.1080p.HEVC.x265.PRT[XvX]/[XvX]Endorsed by torrentgalaxy.to .nfo"},{"trashed":"/home/luisca/.local/share/vifm/Trash/000_SpankBang.com_[反差女王婊] dominatrix \"r*per hunter\" is broken PMV_1080p.mp4","original":"/home/luisca/Downloads/The Great PMV Archive/ 女王レイパー/SpankBang.com_[反差女王婊] dominatrix \"r*per hunter\" is broken PMV_1080p.mp4"},{"trashed":"/home/luisca/.local/share/vifm/Trash/000_SpankBang.com_[反差女王婊]dominatrix dungeon PMV_1080p.mp4","original":"/home/luisca/Downloads/The Great PMV Archive/ 女王レイパー/SpankBang.com_[反差女王婊]dominatrix dungeon PMV_1080p.mp4"},{"trashed":"/home/luisca/.local/share/vifm/Trash/000_[Onlyfans] NoodleDude - Ultimate TikTok PMV 2 v1.1.mp4","original":"/home/luisca/Downloads/[Onlyfans] NoodleDude - Ultimate TikTok PMV 2 v1.1.mp4"},{"trashed":"/home/luisca/.local/share/vifm/Trash/000_desktop.png","original":"/home/luisca/Downloads/desktop.png"},{"trashed":"/home/luisca/.local/share/vifm/Trash/000_favicon_package_v0.16.zip","original":"/home/luisca/Downloads/favicon_package_v0.16.zip"},{"trashed":"/home/luisca/.local/share/vifm/Trash/000_hero.mp4","original":"/home/luisca/Downloads/hero.mp4"},{"trashed":"/home/luisca/.local/share/vifm/Trash/000_mobile.png","original":"/home/luisca/Downloads/mobile.png"},{"trashed":"/home/luisca/.local/share/vifm/Trash/000_noodledude-dick-hero-pmv-60fps-4k-480p_60fps.mp4","original":"/home/luisca/Downloads/noodledude-dick-hero-pmv-60fps-4k-480p_60fps.mp4"},{"trashed":"/home/luisca/.local/share/vifm/Trash/000_org.telegram.desktop.flatpakref","original":"/home/luisca/Downloads/org.telegram.desktop.flatpakref"},{"trashed":"/home/luisca/.local/share/vifm/Trash/000_themes example.mp4","original":"/home/luisca/Downloads/themes example.mp4"},{"trashed":"/home/luisca/.local/share/vifm/Trash/000_wallpaper.jpg","original":"/home/luisca/Downloads/wallpaper.jpg"},{"trashed":"/home/luisca/.local/share/vifm/Trash/000_EPORNER.COM - [G4YhtM1kPUi] NoodleDude Cock Hero - PMV 60FPS 4K (1080).mp4","original":"/home/luisca/Videos/porn/EPORNER.COM - [G4YhtM1kPUi] NoodleDude Cock Hero - PMV 60FPS 4K (1080).mp4"},{"trashed":"/home/luisca/.local/share/vifm/Trash/000_POVPerv.24.03.14.Riley.Reid.XXX.1080p.HEVC.x265.PRT.mkv","original":"/home/luisca/Videos/porn/POVPerv.24.03.14.Riley.Reid.XXX.1080p.HEVC.x265.PRT.mkv"},{"trashed":"/home/luisca/.local/share/vifm/Trash/001_POVPerv.24.03.14.Riley.Reid.XXX.1080p.HEVC.x265.PRT.mkv","original":"/home/luisca/Videos/porn/POVPerv.24.03.14.Riley.Reid.XXX.1080p.HEVC.x265.PRT.mkv"},{"trashed":"/home/luisca/.local/share/vifm/Trash/000_SpankBang.com_摩托摇1_1080p.mp4","original":"/home/luisca/Videos/porn/SpankBang.com_摩托摇1_1080p.mp4"},{"trashed":"/home/luisca/.local/share/vifm/Trash/000_SpankBang.com_神木丽pmv_1080p.mp4","original":"/home/luisca/Videos/porn/SpankBang.com_神木丽pmv_1080p.mp4"},{"trashed":"/home/luisca/.local/share/vifm/Trash/000_[Onlyfans] NoodleDude - Ultimate TikTok PMV 2 v1.1.mp4","original":"/home/luisca/Videos/porn/[Onlyfans] NoodleDude - Ultimate TikTok PMV 2 v1.1.mp4"},{"trashed":"/home/luisca/.local/share/vifm/Trash/001_auto-poweroff.log","original":"/home/luisca/blocking-scripts/auto-poweroff.log"},{"trashed":"/home/luisca/.local/share/vifm/Trash/001_block-files.log","original":"/home/luisca/blocking-scripts/block-files.log"},{"trashed":"/home/luisca/.local/share/vifm/Trash/001_block-programs.log","original":"/home/luisca/blocking-scripts/block-programs.log"},{"trashed":"/home/luisca/.local/share/vifm/Trash/001_change-pswd.log","original":"/home/luisca/blocking-scripts/change-pswd.log"},{"trashed":"/home/luisca/.local/share/vifm/Trash/000_logs","original":"/home/luisca/blocking-scripts/logs"},{"trashed":"/home/luisca/.local/share/vifm/Trash/000_auto-poweroff.log","original":"/home/luisca/blocking-scripts/logs/auto-poweroff.log"},{"trashed":"/home/luisca/.local/share/vifm/Trash/000_block-files.log","original":"/home/luisca/blocking-scripts/logs/block-files.log"},{"trashed":"/home/luisca/.local/share/vifm/Trash/000_block-programs.log","original":"/home/luisca/blocking-scripts/logs/block-programs.log"},{"trashed":"/home/luisca/.local/share/vifm/Trash/000_change-pswd.log","original":"/home/luisca/blocking-scripts/logs/change-pswd.log"},{"trashed":"/home/luisca/.local/share/vifm/Trash/000_test.log","original":"/home/luisca/blocking-scripts/logs/test.log"},{"trashed":"/home/luisca/.local/share/vifm/Trash/001_test.log","original":"/home/luisca/blocking-scripts/test.log"},{"trashed":"/home/luisca/.local/share/vifm/Trash/000_hello","original":"/home/luisca/hello"},{"trashed":"/home/luisca/.local/share/vifm/Trash/000_hello.rs","original":"/home/luisca/hello.rs"},{"trashed":"/home/luisca/.local/share/vifm/Trash/000_hello_world","original":"/home/luisca/hello_world"},{"trashed":"/home/luisca/.local/share/vifm/Trash/000_icon.png","original":"/home/luisca/p/Budgetist/public/icon.png"},{"trashed":"/home/luisca/.local/share/vifm/Trash/000_icons.svg","original":"/home/luisca/p/Budgetist/public/icons.svg"},{"trashed":"/home/luisca/.local/share/vifm/Trash/000_logo.png","original":"/home/luisca/p/Budgetist/public/logo.png"},{"trashed":"/home/luisca/.local/share/vifm/Trash/000_site.webmanifest","original":"/home/luisca/p/Budgetist/public/site.webmanifest"},{"trashed":"/home/luisca/.local/share/vifm/Trash/000_.env","original":"/home/luisca/p/nexa-prep/.env"},{"trashed":"/home/luisca/.local/share/vifm/Trash/000_.env.example","original":"/home/luisca/p/nexa-prep/.env.example"},{"trashed":"/home/luisca/.local/share/vifm/Trash/000_.eslintrc.cjs","original":"/home/luisca/p/nexa-prep/.eslintrc.cjs"},{"trashed":"/home/luisca/.local/share/vifm/Trash/001_.gitignore","original":"/home/luisca/p/nexa-prep/.gitignore"},{"trashed":"/home/luisca/.local/share/vifm/Trash/002_.gitignore","original":"/home/luisca/p/nexa-prep/.gitignore"},{"trashed":"/home/luisca/.local/share/vifm/Trash/001_README.md","original":"/home/luisca/p/nexa-prep/README.md"},{"trashed":"/home/luisca/.local/share/vifm/Trash/000_apps","original":"/home/luisca/p/nexa-prep/apps"},{"trashed":"/home/luisca/.local/share/vifm/Trash/000_next-env.d.ts","original":"/home/luisca/p/nexa-prep/next-env.d.ts"},{"trashed":"/home/luisca/.local/share/vifm/Trash/000_next.config.js","original":"/home/luisca/p/nexa-prep/next.config.js"},{"trashed":"/home/luisca/.local/share/vifm/Trash/001_package.json","original":"/home/luisca/p/nexa-prep/package.json"},{"trashed":"/home/luisca/.local/share/vifm/Trash/002_package.json","original":"/home/luisca/p/nexa-prep/package.json"},{"trashed":"/home/luisca/.local/share/vifm/Trash/000_packages","original":"/home/luisca/p/nexa-prep/packages"},{"trashed":"/home/luisca/.local/share/vifm/Trash/000_pnpm-workspace.yml","original":"/home/luisca/p/nexa-prep/pnpm-workspace.yml"},{"trashed":"/home/luisca/.local/share/vifm/Trash/000_postcss.config.cjs","original":"/home/luisca/p/nexa-prep/postcss.config.cjs"},{"trashed":"/home/luisca/.local/share/vifm/Trash/000_prettier.config.js","original":"/home/luisca/p/nexa-prep/prettier.config.js"},{"trashed":"/home/luisca/.local/share/vifm/Trash/000_prisma","original":"/home/luisca/p/nexa-prep/prisma"},{"trashed":"/home/luisca/.local/share/vifm/Trash/000_public","original":"/home/luisca/p/nexa-prep/public"},{"trashed":"/home/luisca/.local/share/vifm/Trash/000_src","original":"/home/luisca/p/nexa-prep/src"},{"trashed":"/home/luisca/.local/share/vifm/Trash/000_tailwind.config.ts","original":"/home/luisca/p/nexa-prep/tailwind.config.ts"},{"trashed":"/home/luisca/.local/share/vifm/Trash/000_tooling","original":"/home/luisca/p/nexa-prep/tooling"},{"trashed":"/home/luisca/.local/share/vifm/Trash/001_tsconfig.json","original":"/home/luisca/p/nexa-prep/tsconfig.json"},{"trashed":"/home/luisca/.local/share/vifm/Trash/000_.gitignore","original":"/home/luisca/p/r/.gitignore"},{"trashed":"/home/luisca/.local/share/vifm/Trash/000_README.md","original":"/home/luisca/p/r/README.md"},{"trashed":"/home/luisca/.local/share/vifm/Trash/000_bun.lockb","original":"/home/luisca/p/r/bun.lockb"},{"trashed":"/home/luisca/.local/share/vifm/Trash/000_index.ts","original":"/home/luisca/p/r/index.ts"},{"trashed":"/home/luisca/.local/share/vifm/Trash/000_package.json","original":"/home/luisca/p/r/package.json"},{"trashed":"/home/luisca/.local/share/vifm/Trash/000_tsconfig.json","original":"/home/luisca/p/r/tsconfig.json"},{"trashed":"/home/luisca/.local/share/vifm/Trash/001_wallpaper.jpg","original":"/home/luisca/wallpaper.jpg"},{"trashed":"/home/luisca/.local/share/vifm/Trash/002_wallpaper.jpg","original":"/home/luisca/wallpaper.jpg"},{"trashed":"/home/luisca/.local/share/vifm/Trash/003_wallpaper.jpg","original":"/home/luisca/wallpaper.jpg"},{"trashed":"/home/luisca/.local/share/vifm/Trash/004_wallpaper.jpg","original":"/home/luisca/wallpaper.jpg"},{"trashed":"/home/luisca/.local/share/vifm/Trash/005_wallpaper.jpg","original":"/home/luisca/wallpaper.jpg"},{"trashed":"/home/luisca/.local/share/vifm/Trash/000_“Screenshot","original":"/home/luisca/“Screenshot"},{"trashed":"/home/luisca/.local/share/vifm/Trash/000_“Screenshot_000","original":"/home/luisca/“Screenshot_000"}],"marks":{"1":{"dir":"/home/luisca/Music","file":"(playlist_jazz) 시끄럽지 않고 담백한 재즈 모음.mp4","ts":1711682604},"2":{"dir":"/home/luisca/blocking-scripts","file":"..","ts":1711682919},"3":{"dir":"/etc/systemd/system","file":"getty.target.wants","ts":1711682936},"4":{"dir":"/home/luisca/Documents/vifm-tests","file":"..","ts":1711683090},"H":{"dir":"/home/luisca/","file":"..","ts":1685502866},"a":{"dir":"/home/luisca/Documents/scripts/lua","file":"test.lua","ts":1711680553},"b":{"dir":"/home/luisca/bin/","file":"..","ts":1685502892},"h":{"dir":"/home/luisca/","file":"..","ts":1711683268},"j":{"dir":"/home/luisca/Documents/vifm-tests","file":"test3(15).md","ts":1711681355},"k":{"dir":"/home/luisca/Documents","file":"obsidian-vaults","ts":1711680750},"z":{"dir":"/home/luisca/.config/vifm","file":"..","ts":1685502866}},"bmarks":{},"cmd-hist":[{"text":"pushd ~/.local/share/rofi/themes/","ts":1685505042},{"text":"pushd /usr/share/rofi/themes/","ts":1685505042},{"text":"ls -la","ts":1685506569},{"text":"pushd ~/p/","ts":1685506569},{"text":"pushd ~/.local/share/rofi/","ts":1685506569},{"text":"pushd ~/p/dotfiles/rofi/","ts":1685506571},{"text":"pushd ","ts":1685507468},{"text":"select *","ts":1685507468},{"text":"mkdir picom/picom.conf","ts":1685576393},{"text":"mkdir picom","ts":1685576393},{"text":"touch picom.conf","ts":1685576393},{"text":"cp /etc/xdg/picom.conf >> .","ts":1685576393},{"text":"pushd","ts":1685576393},{"text":"popd","ts":1685576393},{"text":"pushd /etc/xdg/picom/","ts":1685576393},{"text":"h vifm-colors","ts":1685640257},{"text":"qw","ts":1685641936},{"text":"pushd /usr/share/backgrounds/arcolinux","ts":1685660496},{"text":"pushd .config/awesome/themes/","ts":1685663135},{"text":"pushd ~/Pictures/","ts":1685730233},{"text":"pushd ~","ts":1685816170},{"text":"pushd .local/share/rofi/themes/","ts":1685840414},{"text":"pushd ~/.dotfiles/rofi/","ts":1685840414},{"text":"pushd ~/.config/","ts":1685987993},{"text":"pushd ~/.dotfiles/","ts":1685987993},{"text":"mv ","ts":1685991258},{"text":"pushd .config","ts":1686021618},{"text":"nmap","ts":1688435119},{"text":"pushd ~/p/hiperbarica-clinic/","ts":1688435119},{"text":"only","ts":1711680804},{"text":"cd ","ts":1711680804},{"text":"test","ts":1711681953},{"text":"touch test2.md","ts":1711681953},{"text":"mkdir vifm-tests/test.md","ts":1711681953},{"text":"mkdir vifm-tests","ts":1711681953},{"text":"mkdir test","ts":1711681953},{"text":"touch new.md","ts":1711681953},{"text":"cd ~/Pictures","ts":1711681953},{"text":"?","ts":1711681953},{"text":"cd Music/","ts":1711681988},{"text":"clear","ts":1711683266},{"text":"cd /etc/systemd/system/","ts":1711683266},{"text":"marks","ts":1711683266},{"text":"cd ~/Documents/vifm-tests/","ts":1711683266},{"text":"mkdir ","ts":1711683266},{"text":"source ~/.config/","ts":1711683266},{"text":"touch test.md","ts":1711683328},{"text":"touch ","ts":1711683385},{"text":"touch test.md test2.md","ts":1711683500},{"text":"file","ts":1711683500},{"text":"cd ~/Music/","ts":1711683500},{"text":"touch oh.md","ts":1711683828},{"text":"cd ~/Pictures/","ts":1711684461},{"text":"cd ~/p/Budgetist/","ts":1711684518},{"text":"!alacritty","ts":1711684733},{"text":"!alacritty &","ts":1711684733},{"text":"cd .config/","ts":1711808120},{"text":"cd ~/.config","ts":1711808120},{"text":"touch poweroff-on-schedule.service","ts":1711841746},{"text":"cd blocking-scripts/","ts":1711845339},{"text":"mkdir logs","ts":1711847559},{"text":"rename 's/\\.sh$/\\.log/' *.sh","ts":1711847559},{"text":"touch auto-poweroff.log","ts":1711847559},{"text":"find ../T","ts":1711847559},{"text":"help","ts":1711847559},{"text":"cd ~/D","ts":1711854689},{"text":"cd /app","ts":1711854689},{"text":"cd ~/.var/app/com.usebottles.bottles/","ts":1711854689},{"text":"cd","ts":1711890210},{"text":"cd ~/Documents/books/","ts":1712288930},{"text":"!xdg-open %c","ts":1712361661},{"text":"!vivaldi %c","ts":1712362425},{"text":"copy Resume.pdf","ts":1712461013},{"text":"cd /etc/NetworkManager/","ts":1712527323},{"text":"q","ts":1712528936},{"text":"cd ~/Pictures/photos/","ts":1712538828},{"text":"c","ts":1712540153},{"text":"cd ~/p/Budgetist/public/","ts":1712635037},{"text":"cd ~","ts":1713047539},{"text":"cd ~/usb","ts":1713051529},{"text":"cxk","ts":1713051530},{"text":"cd /disks/games/Games/","ts":1713199824},{"text":"cd ~/Downloads/","ts":1713242159},{"text":"cd ~/Videos/porn/","ts":1713283386},{"text":"cd ~/Videos/courses/","ts":1713388512},{"text":"cd ~/Documents/shared-misc/","ts":1713627584},{"text":"cd ~/Videos/","ts":1713840313},{"text":"cd ~/p/r/","ts":1715037210},{"text":"cd ~/p/","ts":1715301695},{"text":"cd ~/Documents/obsidian-vaults/","ts":1715893920},{"text":"cd /disks/games/","ts":1717128209},{"text":"cd ~/Documents/","ts":1725295426}],"search-hist":[{"text":"fores","ts":1685505042},{"text":"nvi","ts":1685507468},{"text":"bg0 = '#1E2326'","ts":1685636204},{"text":"bg1 = '#272E33'","ts":1685636204},{"text":"bg2 = '#2E383C'","ts":1685636204},{"text":"bg3 = '#374145'","ts":1685636204},{"text":"bg4 = '#414B50'","ts":1685636204},{"text":"bg5 = '#495156'","ts":1685636204},{"text":"bg6 = '#4F5B58'","ts":1685636204},{"text":"bg7 = '#4C3743'","ts":1685636204},{"text":"bg8 = '#493B40'","ts":1685636204},{"text":"bg9 = '#3C4841'","ts":1685636204},{"text":"bg10 = '#384B55'","ts":1685636204},{"text":"bg11 = '#45443c'","ts":1685636204},{"text":"fg = '#D3C6AA'","ts":1685636204},{"text":"red = '#E67E80'","ts":1685636204},{"text":"orange = '#E69875'","ts":1685636204},{"text":"yellow = '#DBBC7F'","ts":1685636204},{"text":"green = '#A7C080'","ts":1685636204},{"text":"cyan = '#83C092'","ts":1685636204},{"text":"blue = '#7FBBB3'","ts":1685636204},{"text":"magenta = '#D699B6'","ts":1685636204},{"text":"grey0 = '#7A8478'","ts":1685636204},{"text":"grey1 = '#859289'","ts":1685636204},{"text":"grey2 = '#9DA9A0'","ts":1685636204},{"text":"statusline_active_bg = '#A7C080'","ts":1685636204},{"text":"statusline_active_fg = '#D3C6AA'","ts":1685636204},{"text":"statusline_inactive_bg = '#E67E80'","ts":1685636204},{"text":"pushd ~/.config","ts":1685987993},{"text":"select","ts":1688435119},{"text":"lua","ts":1711680804},{"text":"cd ~/Pictures","ts":1711681953},{"text":"app","ts":1711681953},{"text":"'","ts":1711683266},{"text":"help","ts":1711843594},{"text":"bot","ts":1711854689}],"prompt-hist":[{"text":"jjTemplates","ts":1685503864},{"text":"wallpaper.jpg","ts":1685660755},{"text":"screensh.jpg","ts":1685995248},{"text":"mobile.png","ts":1688435119},{"text":"desktop.png","ts":1688435119},{"text":"photos(3)","ts":1711680804},{"text":"idk.md","ts":1711681953},{"text":"idk2.md","ts":1711681953},{"text":"test.mdd","ts":1711681953},{"text":"test-renamed.md","ts":1711681953},{"text":"test3.md","ts":1711681953},{"text":"test.md","ts":1711683266},{"text":"test2.md","ts":1711683266},{"text":"default-avatar.jpga","ts":1711683500},{"text":"default-avatar.jpg","ts":1711683500},{"text":"test1.md","ts":1711683500},{"text":"kkthemes example.mp4","ts":1711807340},{"text":"themes example.mp4","ts":1711807340},{"text":"auto-poweroff.log","ts":1711847559},{"text":"block-files.log","ts":1711847559},{"text":"block-programs.log","ts":1711847559},{"text":"change-pswd.log","ts":1711847559},{"text":"test.log","ts":1711847559}],"regs":{"\"":["/disks/games/The Great PMV Archive/AM1969/SpankBang.com_daddy+a+pmv+by+am1969_1080p.mp4","/disks/games/The Great PMV Archive/AM1969/SpankBang.com_porn+music+video+daddy_1080p.mp4"]},"dir-stack":[{"left-dir":"/home/luisca/Documents","left-file":"hex-to-xterm.py","right-dir":"/","right-file":"opt"},{"left-dir":"/home/luisca/p/awesome-copycats/themes/steamburn","left-file":"icons","right-dir":"/home/luisca","right-file":"Public"},{"left-dir":"/home/luisca/p/dotfiles/awesome/themes/gruv/icons","left-file":"tile.png","right-dir":"/home/luisca/.config/awesome/themes/forest/icons","right-file":"tilebottom.png"},{"left-dir":"/home/luisca/p/dotfiles/awesome/themes/gruv/icons","left-file":"tile.png","right-dir":"/home/luisca","right-file":"2023-06-02-132239_1920x1080_scrot.png"},{"left-dir":"/home/luisca/p/dotfiles/awesome/themes/gruv/icons","left-file":"tile.png","right-dir":"/home/luisca","right-file":"Templates"},{"left-dir":"/home/luisca/p/dotfiles/awesome/themes/gruv/icons","left-file":"tile.png","right-dir":"/home/luisca/.local/share/rofi/themes","right-file":"squared-everforest.rasi"},{"left-dir":"/","left-file":"opt","right-dir":"/","right-file":"proc"},{"left-dir":"/","left-file":"opt","right-dir":"/","right-file":"root"},{"left-dir":"/","left-file":"opt","right-dir":"/home/luisca/.config","right-file":"QtProject.conf"},{"left-dir":"/home/luisca","left-file":"..","right-dir":"/home/luisca","right-file":"Public"},{"left-dir":"/home/luisca/Downloads","left-file":"android-ROM","right-dir":"/home/luisca/Downloads","right-file":"delightfulhug-mfc_0013.jpg"}],"use-term-multiplexer":false}